fluepdot/__init__.py
fluepdot/__main__.py
fluepdot-0.1.1.dist-info/WHEEL
fluepdot-0.1.1.dist-info/METADATA
fluepdot-0.1.1.dist-info/RECORD
