Metadata-Version: 2.1
Name: fluepdot
Version: 0.1.1
Summary: A wrapper for the Fluepdot HTTP API
License: MIT
Author: Carl Gödecken
Author-email: m@mastercarl.com
Requires-Python: >=3.7,<4.0
Classifier: License :: OSI Approved :: MIT License
Classifier: Programming Language :: Python :: 3
Classifier: Programming Language :: Python :: 3.7
Classifier: Programming Language :: Python :: 3.8
Requires-Dist: pillow (>=7.0.0,<8.0.0)
